{
    "facebookAuth" : {
        "clientId": "",
        "clientSecret": "",
        "callbackURL": ""	
    },
    "googleAuth" : {
		"clientId": "",
		"clientSecret": "",
		"callbackURL": ""	
	},
    "NOAUTH_APIS": [
        "/users/register",
        "/users/verify",
        "/users/login",
        "/users/forgetPassword", 
        "/users/confirmPassword", 
        "/users/resendOtp",
        "/auth/facebook", 
        "/auth/facebook/callback", 
        "/auth/google", 
        "/auth/google/callback",  
        "/auth/google/token", 
        "/auth/facebook/token"
    ]
}